{"page":0,"size":50,"total":3,"entities":[{"id":1,"publishDate":1548835200000,"publishTime":1548835840000,"article":"TestArtical.","companyId":1,"companyName":"TestCompany","companyWebsiteUrl":"www.Test.com","companyIconFileName16":"F/small/png/c/5/d/c/d/a43b77xyz.png","companyIconFileName32":"F/large/png/4/2/3/7/e/b60aa9xyz.png","personId":0,"personName":"","intelCategories":[{"id":109,"name":"Accounting","displayName":"Accounting"},{"id":67,"name":"Analytics&Insights","displayName":"Analytics&Insights"}],"persons":[],"types":[{"id":21,"name":"Project","groupId":4,"groupName":"OpportunityScoops"}],"displayDate":1548835200000,"formattedArticle":"Amid-levelsourcehasindicatedthatinitiativesrelatedtoaccountinganalyticshavebeencompletedwithinthelast6months.","type":{"id":0,"displayName":"None"}},{"id":2,"publishDate":1548835200000,"publishTime":1548835840000,"article":"TestArtical2.","companyId":2,"companyName":"TestCompany","companyWebsiteUrl":"www.Test.com","companyIconFileName16":"F/small/png/c/5/d/c/d/a43b77xyz.png","companyIconFileName32":"F/large/png/4/2/3/7/e/b60aa9xyz.png","personId":0,"personName":"","intelCategories":[{"id":109,"name":"Accounting","displayName":"Accounting"},{"id":67,"name":"Analytics&Insights","displayName":"Analytics&Insights"}],"persons":[],"types":[{"id":21,"name":"Project","groupId":4,"groupName":"OpportunityScoops"}],"displayDate":1548835200000,"formattedArticle":"Amid-levelsourcehasindicatedthatinitiativesrelatedtoaccountinganalyticshavebeencompletedwithinthelast6months.","type":{"id":0,"displayName":"None"}},{"id":3,"publishDate":1548835200000,"publishTime":1548835840000,"article":"TestArtical3.","companyId":3,"companyName":"TestCompany","companyWebsiteUrl":"www.Test.com","companyIconFileName16":"F/small/png/c/5/d/c/d/a43b77xyz.png","companyIconFileName32":"F/large/png/4/2/3/7/e/b60aa9xyz.png","personId":0,"personName":"","intelCategories":[{"id":109,"name":"Accounting","displayName":"Accounting"},{"id":67,"name":"Analytics&Insights","displayName":"Analytics&Insights"}],"persons":[],"types":[{"id":21,"name":"Project","groupId":4,"groupName":"OpportunityScoops"}],"displayDate":1548835200000,"formattedArticle":"Amid-levelsourcehasindicatedthatinitiativesrelatedtoaccountinganalyticshavebeencompletedwithinthelast6months.","type":{"id":0,"displayName":"None"}}]}